terminate.py
terminate-0.0.9.dist-info/METADATA
terminate-0.0.9.dist-info/WHEEL
terminate-0.0.9.dist-info/top_level.txt
terminate-0.0.9.dist-info/RECORD
