Metadata-Version: 2.4
Name: terminate
Version: 0.0.9
Summary: Different ways to exit program.
Author-email: Kor Shantanu Nitin <korshantanu@gmail.com>
Project-URL: Homepage, https://github.com/putterPatcher/deciml
Project-URL: Issues, https://github.com/putterPatcher/deciml/issues
Classifier: Programming Language :: Python :: 3
Classifier: Operating System :: OS Independent
Requires-Python: >=3.8
